Metadata-Version: 1.0
Name: at101-distributions
Version: 0.1
Summary: Gaussian distributions
Home-page: UNKNOWN
Author: Alex Terry
Author-email: UNKNOWN
License: UNKNOWN
Platform: UNKNOWN
